shpm/__init__.py
shpm/__main__.py
shpm_themadpunter-1.0.0.dist-info/LICENSE
shpm_themadpunter-1.0.0.dist-info/METADATA
shpm_themadpunter-1.0.0.dist-info/WHEEL
shpm_themadpunter-1.0.0.dist-info/top_level.txt
shpm_themadpunter-1.0.0.dist-info/RECORD
