Metadata-Version: 2.1
Name: shpm-themadpunter
Version: 1.0.0
Summary: A package manager for MIT Scratch
Author: Themadpunter
Author-email: TheMadPunter <themadpunter10@gmail.com>
Project-URL: Homepage, https://github.com/familycomicsstudios/ShredPackageManager
Project-URL: Bug Tracker, https://github.com/familycomicsstudios/ShredPackageManager/issues
Classifier: Programming Language :: Python :: 3
Classifier: License :: OSI Approved :: MIT License
Classifier: Operating System :: OS Independent
Requires-Python: >=3.7
License-File: LICENSE
Requires-Dist: flask (>2.2.0)
Requires-Dist: requests
